aiocogeo_tiler/__init__.py
aiocogeo_tiler/tiler.py
aiocogeo_tiler-0.1.1.dist-info/LICENSE
aiocogeo_tiler-0.1.1.dist-info/METADATA
aiocogeo_tiler-0.1.1.dist-info/WHEEL
aiocogeo_tiler-0.1.1.dist-info/top_level.txt
aiocogeo_tiler-0.1.1.dist-info/RECORD
