Metadata-Version: 2.1
Name: aiocogeo-tiler
Version: 0.1.1
Summary: Asynchronous cogeotiff tiler
Home-page: https://github.com/geospatial-jeff/aiocogeo-tiler
Author: Jeff Albrecht
Author-email: geospatialjeff@gmail.com
License: mit
Keywords: cogeo COG
Platform: UNKNOWN
Classifier: Intended Audience :: Developers
Classifier: Intended Audience :: Information Technology
Classifier: Intended Audience :: Science/Research
Classifier: Programming Language :: Python :: 3.6
Classifier: Programming Language :: Python :: 3.7
Classifier: Programming Language :: Python :: 3.8
Classifier: License :: OSI Approved :: MIT License
Requires-Python: >=3.7
Requires-Dist: aiocogeo (==0.3.*)
Requires-Dist: morecantile
Requires-Dist: rasterio (>=1.1.7)
Requires-Dist: rio-tiler (==2.0.0rc2)
Provides-Extra: dev
Requires-Dist: mercantile ; extra == 'dev'
Requires-Dist: rasterio ; extra == 'dev'
Requires-Dist: pytest (<5.4) ; extra == 'dev'
Requires-Dist: pytest-asyncio (<0.11.0) ; extra == 'dev'
Requires-Dist: pytest-cov ; extra == 'dev'
Requires-Dist: shapely ; extra == 'dev'
Requires-Dist: aioboto3 ; extra == 'dev'
